tractoray/__init__.py
tractoray/cli/bootstrapper.py
tractoray/cli/cli.py
tractoray/errors.py
tractoray/internal/bootstrap.py
tractoray/internal/coordinator.py
tractoray/internal/logs.py
tractoray/internal/ray.py
tractoray/internal/utils.py
tractoray/jupyter.py
tractoray/runner.py
tractoray/ytpath.py
tractoray-0.0.12.dist-info/METADATA
tractoray-0.0.12.dist-info/WHEEL
tractoray-0.0.12.dist-info/entry_points.txt
tractoray-0.0.12.dist-info/RECORD
